setup.py
tobin/__init__.py
tobin/base.py
tobin.egg-info/PKG-INFO
tobin.egg-info/SOURCES.txt
tobin.egg-info/dependency_links.txt
tobin.egg-info/requires.txt
tobin.egg-info/top_level.txt