Metadata-Version: 1.0
Name: tobin
Version: 0.0.1
Summary: Schematics, Data, and Databases
Home-page: http://github.com/j2labs/tobin
Author: James Dennis
Author-email: jdennis@gmail.com
License: UNKNOWN
Platform: UNKNOWN
